datastage/__init__.py
datastage/common.py
datastage/datastage_v3.py
datastage/version.py
datastage-0.0.1.dist-info/LICENSE
datastage-0.0.1.dist-info/METADATA
datastage-0.0.1.dist-info/WHEEL
datastage-0.0.1.dist-info/top_level.txt
datastage-0.0.1.dist-info/zip-safe
datastage-0.0.1.dist-info/RECORD
