Metadata-Version: 2.1
Name: datastage
Version: 0.0.1
Summary: IBM DataStage SDK for Python
Home-page: https://github.com/IBM/datastage-python-sdk
Author: IBM
Author-email: dsusbld@us.ibm.com
License: Apache 2.0
Keywords: datastage
Platform: UNKNOWN
Classifier: Programming Language :: Python
Classifier: Programming Language :: Python :: 3
Classifier: Programming Language :: Python :: 3.6
Classifier: Programming Language :: Python :: 3.7
Classifier: Programming Language :: Python :: 3.8
Classifier: Programming Language :: Python :: 3.9
Classifier: Development Status :: 4 - Beta
Classifier: Intended Audience :: Developers
Classifier: License :: OSI Approved :: Apache Software License
Classifier: Operating System :: OS Independent
Classifier: Topic :: Software Development :: Libraries :: Python Modules
Classifier: Topic :: Software Development :: Libraries :: Application Frameworks
License-File: LICENSE
Requires-Dist: requests (<3.0,>=2.24.0)
Requires-Dist: python-dateutil (<3.0.0,>=2.5.3)
Requires-Dist: ibm-cloud-sdk-core (>=3.4.0)
